karyopype/__init__.py
karyopype/karyopype.py
karyopype/data/chromsizes/gorGor3.chrom.sizes
karyopype/data/chromsizes/hg19.chrom.sizes
karyopype/data/chromsizes/hg38.chrom.sizes
karyopype/data/chromsizes/mm10.chrom.sizes
karyopype/data/chromsizes/nomLeu3.chrom.sizes
karyopype/data/chromsizes/panTro4.chrom.sizes
karyopype/data/chromsizes/rheMac8.chrom.sizes
test/__init__.py
test/test_genomes.py
test/test_karyopype.py
karyopype-0.1.6.dist-info/LICENSE
karyopype-0.1.6.dist-info/METADATA
karyopype-0.1.6.dist-info/WHEEL
karyopype-0.1.6.dist-info/top_level.txt
karyopype-0.1.6.dist-info/RECORD
