Metadata-Version: 2.1
Name: karyopype
Version: 0.1.6
Summary: Chromosomal visualization in Python.
Home-page: http://github.com/jakevc/karyopype
Author: Jake VanCampen
Author-email: jake.vancampen7@gmail.com
License: MIT
Keywords: Bioinformatics
Platform: UNKNOWN
Classifier: Programming Language :: Python :: 3
Classifier: Development Status :: 4 - Beta
Classifier: Environment :: Other Environment
Classifier: Intended Audience :: Developers
Classifier: Intended Audience :: Science/Research
Classifier: License :: OSI Approved :: MIT License
Classifier: Operating System :: POSIX :: Linux
Classifier: Operating System :: MacOS :: MacOS X
Classifier: Topic :: Scientific/Engineering
Requires-Dist: matplotlib
Requires-Dist: pandas
Requires-Dist: numpy
